README.md
pysafecircuit/__init__.py
pysafecircuit/pysafecircuit.py
pysafecircuit-0.1.1.dist-info/METADATA
pysafecircuit-0.1.1.dist-info/WHEEL
pysafecircuit-0.1.1.dist-info/RECORD
